[{"label":"Game","value":"502"},{"label":"Bulk Bricks","value":"254"},{"label":"My Own Train","value":"238"},{"label":"Star Wars","value":"158"},{"label":"9V","value":"236"},{"label":"Bionicle","value":"324"},{"label":"Sculptures","value":"276"},{"label":"Spider-Man","value":"488"},{"label":"Clikits","value":"500"},{"label":"Basketball","value":"459"},{"label":"Star Wars Episode 4/5/6","value":"169"},{"label":"Harry Potter","value":"246"},{"label":"Airport","value":"53"},{"label":"Knights Kingdom I","value":"197"},{"label":"Fantasy Era","value":"193"},{"label":"Star Wars Clone Wars","value":"165"},{"label":"Titans","value":"347"},{"label":"Creator","value":"22"},{"label":"Desert","value":"297"},{"label":"NXT","value":"259"},{"label":"Disney Princess","value":"579"},{"label":"Basic Set","value":"37"},{"label":"Juniors","value":"591"},{"label":"Extreme Team","value":"87"},{"label":"Super Heroes","value":"482"},{"label":"Animals","value":"496"},{"label":"Friends","value":"494"},{"label":"Advent Sub-Set","value":"217"},{"label":"Batman","value":"484"},{"label":"Ninja","value":"434"},{"label":"Classic Basic","value":"470"},{"label":"Space Port","value":"93"},{"label":"Ninjago","value":"435"},{"label":"Life On Mars","value":"135"},{"label":"Town","value":"50"},{"label":"RoboRiders","value":"16"},{"label":"Classic Basic","value":"221"},{"label":"Studios","value":"273"},{"label":"Soccer","value":"462"},{"label":"Freestyle","value":"399"},{"label":"Fire","value":"58"},{"label":"Master Building Academy","value":"432"},{"label":"Heroes","value":"401"},{"label":"Minecraft","value":"577"},{"label":"Villains","value":"403"},{"label":"Elves","value":"600"},{"label":"Nexo Knights","value":"605"},{"label":"City","value":"220"},{"label":"Traffic","value":"63"},{"label":"Construction","value":"56"},{"label":"Police","value":"61"},{"label":"City","value":"52"},{"label":"Tiny Turbos","value":"120"},{"label":"Atlantis","value":"315"},{"label":"Cars","value":"269"},{"label":"Avengers","value":"487"},{"label":"Ferrari","value":"114"},{"label":"Mini","value":"159"},{"label":"Legends of Chima","value":"571"},{"label":"Teenage Mutant Ninja Turtles","value":"570"},{"label":"The LEGO Movie","value":"578"},{"label":"Designer Sets","value":"204"},{"label":"LEGO Brand Store","value":"408"},{"label":"Friends","value":"226"},{"label":"Star Wars Episode 1","value":"166"},{"label":"Orient Expedition","value":"300"},{"label":"RCX","value":"260"},{"label":"Exo-Force","value":"389"},{"label":"Key Chain","value":"503"},{"label":"Monthly Mini Model Build","value":"409"},{"label":"Legoland Parks","value":"425"},{"label":"Creator","value":"223"},{"label":"Drome Racers","value":"113"},{"label":"Supplemental","value":"48"},{"label":"Star Wars Episode 2","value":"167"},{"label":"Power Miners","value":"439"},{"label":"Star Wars Other","value":"170"},{"label":"Knights Kingdom II","value":"198"},{"label":"Star Wars Rebels","value":"182"},{"label":"Speed Champions","value":"601"},{"label":"Fairy-Tale","value":"319"},{"label":"Star Wars Episode 3","value":"168"},{"label":"Pirates","value":"224"},{"label":"Rahkshi","value":"344"},{"label":"Power Racers","value":"116"},{"label":"Speedorz","value":"572"},{"label":"The Simpsons","value":"550"},{"label":"Dimensions","value":"604"},{"label":"Star Wars","value":"225"},{"label":"Clikits","value":"222"},{"label":"Belville","value":"218"},{"label":"Castle","value":"219"}]